wethenew/__init__.py
wethenew/__version__.py
wethenew/_helpers.py
wethenew/_http_manager.py
wethenew/_proxy_manager.py
wethenew/main.py
wethenew/models.py
wethenew_client-1.0.1.dist-info/LICENSE
wethenew_client-1.0.1.dist-info/METADATA
wethenew_client-1.0.1.dist-info/WHEEL
wethenew_client-1.0.1.dist-info/top_level.txt
wethenew_client-1.0.1.dist-info/RECORD
