Metadata-Version: 2.1
Name: wethenew-client
Version: 1.0.1
Summary: wethenew-client is a robust and user-friendly client library designed to simplify interactions with the wethenew API. It provides developers with an intuitive interface to access and manipulate data, streamlining the integration of wethenew services into various applications.
Home-page: https://github.com/niewiemczego/wethenew-client
Author: niewiemczego
License: MIT
Keywords: wethenew snekaers rest api restocks stockx goat klekt
Classifier: Intended Audience :: Developers
Classifier: License :: OSI Approved :: MIT License
Classifier: Operating System :: OS Independent
Classifier: Programming Language :: Python :: 3
Classifier: Programming Language :: Python :: 3.9
Classifier: Programming Language :: Python :: 3.10
Classifier: Programming Language :: Python :: 3.11
Classifier: Programming Language :: Python
Classifier: Topic :: Software Development :: Libraries :: Python Modules
License-File: LICENSE
Requires-Dist: cloudscraper
Requires-Dist: playwright
Requires-Dist: undetected-playwright
